iniparser/__init__.py
iniparser/exceptions.py
iniparser/helper.py
iniparser/iniparser.py
test/__init__.py
test/test_functions.py
config_env_parser-0.0.3.dist-info/METADATA
config_env_parser-0.0.3.dist-info/WHEEL
config_env_parser-0.0.3.dist-info/top_level.txt
config_env_parser-0.0.3.dist-info/RECORD
