Metadata-Version: 2.1
Name: config-env-parser
Version: 0.0.3
Summary: Configuration parser with all variables possible to overwrite by environment variables
Home-page: https://gitlab.com/jockel/config-env-parser.git
Author: Jochen Gietzen
Author-email: dev@gietzen.org
License: UNKNOWN
Platform: UNKNOWN
Classifier: Programming Language :: Python :: 3
Classifier: License :: OSI Approved :: MIT License
Classifier: Operating System :: OS Independent
Requires-Python: >=3.6
